worldbank_api/__init__.py
worldbank_api/indicators.py
worldbank_api-0.1.0.dist-info/METADATA
worldbank_api-0.1.0.dist-info/WHEEL
worldbank_api-0.1.0.dist-info/top_level.txt
worldbank_api-0.1.0.dist-info/RECORD
