Metadata-Version: 2.4
Name: worldbank_api
Version: 0.1.0
Summary: Analyse des données économiques via l’API World Bank
Author-email: Diallo <saikoudiallo125@gmail.com>
Requires-Dist: requests
Requires-Dist: pandas
